addtestpypi/__init__.py
addtestpypi-2.0.3.dist-info/METADATA
addtestpypi-2.0.3.dist-info/WHEEL
addtestpypi-2.0.3.dist-info/top_level.txt
addtestpypi-2.0.3.dist-info/RECORD
