Metadata-Version: 2.1
Name: addtestpypi
Version: 2.0.3
Summary: A simple library for adding numbers
Home-page: https://github.com/yamini-2195/addtestpypi
Author: Yamini
Author-email: kyamini21@gmail.com
